jetdl/_creation.py
jetdl/_C.cpython-311-darwin.so
jetdl/__init__.py
jetdl/random.py
jetdl/linalg.py
jetdl/_manip.py
jetdl/_C.cpython-312-darwin.so
jetdl/tensor.pyi
jetdl/math.py
jetdl/nn/_layers.py
jetdl/nn/_activations.py
jetdl/nn/__init__.py
jetdl/nn/_loss.py
jetdl/nn/_loss.pyi
jetdl/nn/_layers.pyi
jetdl/nn/_objects.py
jetdl/optim/__init__.py
jetdl/optim/_optim.py
jetdl/optim/_sgd.py
jetdl-0.9.0.dist-info/RECORD
jetdl-0.9.0.dist-info/WHEEL
jetdl-0.9.0.dist-info/METADATA
jetdl-0.9.0.dist-info/licenses/LICENSE
