Metadata-Version: 2.2
Name: jetdl
Version: 0.9.0
Summary: A lightweight deep learning framework
Keywords: machine-learning,deep-learning,automatic-differentiation,tensor,neural-networks
Author-Email: Liiban Mohamud <liibanmohamud12@gmail.com>
Maintainer-Email: Liiban Mohamud <liibanmohamud12@gmail.com>
License: MIT
Classifier: Development Status :: 3 - Alpha
Classifier: Intended Audience :: Developers
Classifier: Intended Audience :: Science/Research
Classifier: License :: OSI Approved :: MIT License
Classifier: Operating System :: OS Independent
Classifier: Programming Language :: Python :: 3
Classifier: Programming Language :: Python :: 3.11
Classifier: Programming Language :: Python :: 3.12
Classifier: Programming Language :: Python :: 3.13
Classifier: Programming Language :: Python :: 3.14
Classifier: Topic :: Scientific/Engineering :: Artificial Intelligence
Classifier: Topic :: Software Development :: Libraries :: Python Modules
Requires-Python: >=3.11
Provides-Extra: dev
Requires-Dist: setuptools>=80.9.0; extra == "dev"
Requires-Dist: black>=22.0.0; extra == "dev"
Requires-Dist: isort>=5.0.0; extra == "dev"
Provides-Extra: test
Requires-Dist: pytest>=8.3.4; extra == "test"
